setup.py
pycrest/__init__.py
pycrest/cache.py
pycrest/compat.py
pycrest/errors.py
pycrest/eve.py
pycrest.egg-info/PKG-INFO
pycrest.egg-info/SOURCES.txt
pycrest.egg-info/dependency_links.txt
pycrest.egg-info/requires.txt
pycrest.egg-info/top_level.txt