Metadata-Version: 1.1
Name: pycrest
Version: 0.0.6
Summary: Easy interface to the CREST API
Home-page: https://github.com/pycrest/PyCrest
Author: Dreae
Author-email: penitenttangentt@gmail.com
License: MIT License
Platform: UNKNOWN
Classifier: Development Status :: 4 - Beta
Classifier: Intended Audience :: Developers
Classifier: Programming Language :: Python
Classifier: Programming Language :: Python :: 2.7
Classifier: Programming Language :: Python :: 3
Classifier: Programming Language :: Python :: 3.2
Classifier: Programming Language :: Python :: 3.3
Classifier: Programming Language :: Python :: 3.4
Classifier: Programming Language :: Python :: Implementation :: PyPy
